kitty_doc/__init__.py
kitty_doc/version.py
kitty_doc/backend/__init__.py
kitty_doc/backend/pipeline/__init__.py
kitty_doc/backend/pipeline/batch_analyze.py
kitty_doc/backend/pipeline/model_init.py
kitty_doc/backend/pipeline/model_json_to_middle_json.py
kitty_doc/backend/pipeline/model_list.py
kitty_doc/backend/pipeline/para_split.py
kitty_doc/backend/pipeline/pipeline_analyze.py
kitty_doc/backend/pipeline/pipeline_magic_model.py
kitty_doc/backend/pipeline/pipeline_middle_json_mkcontent.py
kitty_doc/cli/__init__.py
kitty_doc/cli/common.py
kitty_doc/data/__init__.py
kitty_doc/data/data_reader_writer/__init__.py
kitty_doc/data/data_reader_writer/base.py
kitty_doc/data/data_reader_writer/dummy.py
kitty_doc/data/data_reader_writer/filebase.py
kitty_doc/data/data_reader_writer/multi_bucket_s3.py
kitty_doc/data/data_reader_writer/s3.py
kitty_doc/data/io/__init__.py
kitty_doc/data/io/base.py
kitty_doc/data/io/http.py
kitty_doc/data/io/s3.py
kitty_doc/data/utils/__init__.py
kitty_doc/data/utils/exceptions.py
kitty_doc/data/utils/path_utils.py
kitty_doc/data/utils/schemas.py
kitty_doc/model/__init__.py
kitty_doc/model/formula/__init__.py
kitty_doc/model/formula/fix_utils.py
kitty_doc/model/formula/rapid_formula_model.py
kitty_doc/model/formula/rapid_formula_self/__init__.py
kitty_doc/model/formula/rapid_formula_self/main.py
kitty_doc/model/formula/rapid_formula_self/configs/__init__.py
kitty_doc/model/formula/rapid_formula_self/configs/default_models.yaml
kitty_doc/model/formula/rapid_formula_self/configs/engine_cfg.yaml
kitty_doc/model/formula/rapid_formula_self/inference_engine/__init__.py
kitty_doc/model/formula/rapid_formula_self/inference_engine/base.py
kitty_doc/model/formula/rapid_formula_self/inference_engine/openvino.py
kitty_doc/model/formula/rapid_formula_self/inference_engine/onnxruntime/__init__.py
kitty_doc/model/formula/rapid_formula_self/inference_engine/onnxruntime/main.py
kitty_doc-0.1.0.dist-info/licenses/LICENSE
kitty_doc-0.1.0.dist-info/METADATA
kitty_doc-0.1.0.dist-info/WHEEL
kitty_doc-0.1.0.dist-info/top_level.txt
kitty_doc-0.1.0.dist-info/RECORD
