Metadata-Version: 2.4
Name: kitty_doc
Version: 0.1.0
Summary: A practical tool for converting PDF to Markdown
Author: 
Author-email: 
License: Apache 2.0
Project-URL: Home, https://github.com/hzkitty
Project-URL: Repository, https://github.com/hzkitty/KittyDoc
Keywords: kitty-doc, kitty_doc, onnx, convert, pdf, markdown
Classifier: Programming Language :: Python :: 3.10
Classifier: Programming Language :: Python :: 3.11
Classifier: Programming Language :: Python :: 3.12
Classifier: Programming Language :: Python :: 3.13
Requires-Python: >=3.10,<3.14
License-File: LICENSE
Requires-Dist: boto3>=1.28.43
Requires-Dist: loguru>=0.6.0
Requires-Dist: numpy>=1.21.6
Requires-Dist: pdfminer.six==20250506
Requires-Dist: tqdm>=4.67.1
Requires-Dist: requests
Requires-Dist: pypdfium2>=4.30.0
Requires-Dist: pypdf>=5.6.0
Requires-Dist: reportlab
Requires-Dist: pdftext>=0.6.2
Requires-Dist: json-repair>=0.46.2
Requires-Dist: fast-langdetect<0.3.0,>=0.2.3
Requires-Dist: scikit-image<1.0.0,>=0.25.0
Requires-Dist: openai<2,>=1.70.0
Requires-Dist: beautifulsoup4<5,>=4.13.5
Requires-Dist: pydantic<2.11,>=2.7.2
Requires-Dist: matplotlib<4,>=3.10
Requires-Dist: ftfy<7,>=6.3.1
Requires-Dist: shapely<3,>=2.0.7
Requires-Dist: torch<2.8.0,>=2.6.0
Requires-Dist: torchvision
Requires-Dist: onnxruntime>=1.18.0
Requires-Dist: openvino>=2024.6.0
Requires-Dist: tokenizers>=0.13.2
Requires-Dist: rapidocr<=3.3.0,>=3.1.0
Dynamic: classifier
Dynamic: description
Dynamic: description-content-type
Dynamic: keywords
Dynamic: license
Dynamic: license-file
Dynamic: project-url
Dynamic: requires-dist
Dynamic: requires-python
Dynamic: summary
